<?xml version="1.0" encoding="iso-8859-1"?>
<!-- $Id$ -->
<note language="de"
	xmlns="http://www.sos-berlin.com/schema/scheduler_job_documentation_v1.1"
	xmlns:xi="http://www.w3.org/2001/XInclude" xmlns:xhtml="http://www.w3.org/1999/xhtml"
	xmlns:xsi="http://www.w3.org/2001/XMLSchema-instance">
<title>Datei-Aufträge erstellen</title>
			<p>
				Dieser Job kann Datei-Aufträge (file-orders) erzeugen.
				Dabei kann angegeben werden, ob nur für die erste Datei oder für
				alle Dateien in der Ergebnisliste ein Dateiauftrag angelegt werden soll. 
            </p>
                                <p>
            Weiterführende Informationen zu Datei-Aufträgen ("file-orders") finden Sie hier:
            <a href="http://www.sos-berlin.com/doc/de/scheduler.doc/file_orders.xml">
                Directory Monitoring with File Orders
                    </a>
.
        </p>
            
</note>
